<?xml version="1.0"?>
<?xml-stylesheet href="/xslt-orders-route?" type="text/xsl"?>
<orders>
 <orders>
  <OrderID>11</OrderID>
  <Username>ali</Username>
  <TotalPrice>123</TotalPrice>
  <Status>TOSHIP</Status>
  <Address>12,aaa,aaa</Address>
  <DateTime>02:24:02</DateTime>
  <created_at>2022-03-27 02:24:02</created_at>
  <updated_at>2022-04-07 08:39:58</updated_at>
 </orders>
 <orders>
  <OrderID>756725</OrderID>
  <Username>aa@gmail.com</Username>
  <TotalPrice>2099</TotalPrice>
  <Status>TOSHIP</Status>
  <Address>asd, No.16 Jalan Pendekar 21 Lorong 1 Johor Bahru Johor 81300</Address>
  <DateTime>2022-04-07 12:16:14</DateTime>
  <created_at></created_at>
  <updated_at></updated_at>
 </orders>
 <orders>
  <OrderID>755439</OrderID>
  <Username>aa@gmail.com</Username>
  <TotalPrice>5497</TotalPrice>
  <Status>TOSHIP</Status>
  <Address>asd, No.16 Jalan Pendekar 21 Lorong 1 Johor Bahru Johor 81300</Address>
  <DateTime>2022-04-07 12:30:45</DateTime>
  <created_at></created_at>
  <updated_at></updated_at>
 </orders>
 <orders>
  <OrderID>755439</OrderID>
  <Username>aa@gmail.com</Username>
  <TotalPrice>5497</TotalPrice>
  <Status>TOSHIP</Status>
  <Address>asd, No.16 Jalan Pendekar 21 Lorong 1 Johor Bahru Johor 81300</Address>
  <DateTime>2022-04-07 12:30:45</DateTime>
  <created_at></created_at>
  <updated_at></updated_at>
 </orders>
</orders>
